neer_match/__init__.py
neer_match/axiom_generator.py
neer_match/data_generator.py
neer_match/dl_matching_model.py
neer_match/field_pair_network.py
neer_match/global_explainability.py
neer_match/local_explainability.py
neer_match/matching_model.py
neer_match/matching_model_tools.py
neer_match/metrics.py
neer_match/ns_matching_model.py
neer_match/reasoning.py
neer_match/record_pair_network.py
neer_match/similarity_encoding.py
neer_match/similarity_map.py
neer_match-0.8.4.dist-info/licenses/LICENSE.txt
neer_match-0.8.4.dist-info/METADATA
neer_match-0.8.4.dist-info/WHEEL
neer_match-0.8.4.dist-info/top_level.txt
neer_match-0.8.4.dist-info/RECORD
