Metadata-Version: 2.4
Name: neer-match
Version: 0.8.4
Summary: NEural-symbolic Entity Reasoning and Matching
Author-email: Pantelis Karapanagiotis <pikappa.devel@gmail.com>, Marius Liebald <maliedvp@gmail.com>
License-Expression: MIT
Project-URL: Homepage, https://py-neer-match.pikappa.eu/
Project-URL: Documentation, https://py-neer-match.pikappa.eu/
Project-URL: Source Code, https://github.com/pi-kappa-devel/py-neer-match
Project-URL: Bug Tracker, https://github.com/pi-kappa-devel/py-neer-match/issues
Classifier: Environment :: Console
Classifier: Intended Audience :: Developers
Classifier: Intended Audience :: Information Technology
Classifier: Intended Audience :: Science/Research
Classifier: Operating System :: OS Independent
Classifier: Programming Language :: Python :: 3
Classifier: Topic :: Database
Classifier: Topic :: Scientific/Engineering :: Artificial Intelligence
Requires-Python: >=3.10
License-File: LICENSE.txt
Requires-Dist: ltn>=0.0.1
Requires-Dist: matplotlib>=3.5.0
Requires-Dist: numpy>=1.26.4
Requires-Dist: pandas>=2.2.3
Requires-Dist: rapidfuzz>=3.10.1
Requires-Dist: tensorflow>=2.18.0
Requires-Dist: typing>=3.7.4
Provides-Extra: tests
Requires-Dist: pytest; extra == "tests"
Dynamic: license-file
